mxlearn/__init__.py
mxlearn/cli.py
mxlearn/mxlearn.py
mxlearn-0.1.0.dist-info/DESCRIPTION.rst
mxlearn-0.1.0.dist-info/METADATA
mxlearn-0.1.0.dist-info/RECORD
mxlearn-0.1.0.dist-info/WHEEL
mxlearn-0.1.0.dist-info/entry_points.txt
mxlearn-0.1.0.dist-info/metadata.json
mxlearn-0.1.0.dist-info/top_level.txt
