Metadata-Version: 2.0
Name: mxlearn
Version: 0.1.0
Summary: Deep learning library featuring a higher-level API for mxnet.
Home-page: https://github.com/classtag/mxlearn
Author: Duo An
Author-email: anduo@qq.com
License: Apache Software License 2.0
Keywords: mxlearn
Platform: UNKNOWN
Classifier: Development Status :: 2 - Pre-Alpha
Classifier: Intended Audience :: Developers
Classifier: License :: OSI Approved :: Apache Software License
Classifier: Natural Language :: English
Classifier: Programming Language :: Python :: 2
Classifier: Programming Language :: Python :: 2.6
Classifier: Programming Language :: Python :: 2.7
Classifier: Programming Language :: Python :: 3
Classifier: Programming Language :: Python :: 3.3
Classifier: Programming Language :: Python :: 3.4
Classifier: Programming Language :: Python :: 3.5
Requires-Dist: Click (>=6.0)
